<?xml version="1.0" encoding="UTF-8"?>
<beans xmlns="http://www.springframework.org/schema/beans"
       xmlns:xsi="http://www.w3.org/2001/XMLSchema-instance"
       xmlns:p="http://www.springframework.org/schema/p"
       xmlns:util="http://www.springframework.org/schema/util"
       xsi:schemaLocation="
		http://www.springframework.org/schema/beans 
		http://www.springframework.org/schema/beans/spring-beans-3.0.xsd
		http://www.springframework.org/schema/util 
		http://www.springframework.org/schema/util/spring-util-3.0.xsd">

    <!--here all the url value should contains the valid path for the jrxml file-->

	<!-- pdf,xls,html -->
    <bean id="codeReport" class="org.springframework.web.servlet.view.jasperreports.JasperReportsMultiFormatView">
    	<property name="url" value="/WEB-INF/reports/report5.jasper"/>
    	<property name="exporterParameters">
    		<map>
    			<entry key="net.sf.jasperreports.engine.JRExporterParameter.CHARACTER_ENCODING">
    				<value>UTF-8</value>
    			</entry>
             	<entry key="net.sf.jasperreports.engine.export.JRHtmlExporterParameter.IS_USING_IMAGES_TO_ALIGN">
                	<value>false</value>
            	</entry>
            	<!-- 
             	<entry key="net.sf.jasperreports.engine.export.JRHtmlExporterParameter.IMAGES_URI">
                	<value>/resources/images/report/</value>
            	</entry>
             	<entry key="net.sf.jasperreports.engine.export.JRHtmlExporterParameter.IS_REMOVE_EMPTY_SPACE_BETWEEN_ROWS">
                	<value>true</value>
            	</entry>
             	<entry key="net.sf.jasperreports.engine.export.JRHtmlExporterParameter.IS_WHITE_PAGE_BACKGROUND">
                	<value>true</value>
            	</entry>
            	 -->
    		</map>
    	</property>
    </bean>

</beans>